promptgraphtools/__init__.py
promptgraphtools/__main__.py
promptgraphtools/code_autogen/graph_generator.py
promptgraphtools/code_autogen/schema_io.py
promptgraphtools/code_autogen/steps_schema.json
promptgraphtools/core/conditional_router_step.py
promptgraphtools/core/fan_out_step.py
promptgraphtools/core/step.py
promptgraphtools/core/step_graph.py
promptgraphtools/core/base_classes/llm_client.py
promptgraphtools/core/base_classes/step_like.py
promptgraphtools/core/llm_clients/gemini.py
promptgraphtools-0.1.37.dist-info/METADATA
promptgraphtools-0.1.37.dist-info/WHEEL
promptgraphtools-0.1.37.dist-info/entry_points.txt
promptgraphtools-0.1.37.dist-info/licenses/LICENSE
promptgraphtools-0.1.37.dist-info/RECORD
