Metadata-Version: 2.4
Name: promptgraphtools
Version: 0.1.37
Summary: A lightweight, highly concurrent execution graph framework.
Project-URL: Homepage, https://github.com/tucker-weed/prompt-graph-tools
Author-email: Tucker Weed <tuckerweed@gmail.com>
License: The MIT License (MIT)
License-File: LICENSE
Classifier: License :: OSI Approved :: MIT License
Classifier: Operating System :: OS Independent
Classifier: Programming Language :: Python :: 3
Requires-Python: >=3.6
Requires-Dist: google-genai==0.2.2
Requires-Dist: jinja2
